doomarena/promptceptor/__init__.py
doomarena/promptceptor/__main__.py
doomarena/promptceptor/cli.py
doomarena/promptceptor/output.py
doomarena/promptceptor/patch.py
doomarena/promptceptor/replay.py
doomarena/promptceptor/examples/patch_litellm.py
doomarena/promptceptor/examples/patch_openai_chat.py
doomarena/promptceptor/examples/patch_openai_responses.py
doomarena/promptceptor/integrations/__init__.py
doomarena/promptceptor/integrations/base.py
doomarena/promptceptor/integrations/litellm.py
doomarena/promptceptor/integrations/openai_chat.py
doomarena/promptceptor/integrations/openai_responses.py
doomarena_promptceptor-0.0.4.1.dist-info/METADATA
doomarena_promptceptor-0.0.4.1.dist-info/WHEEL
doomarena_promptceptor-0.0.4.1.dist-info/entry_points.txt
doomarena_promptceptor-0.0.4.1.dist-info/top_level.txt
doomarena_promptceptor-0.0.4.1.dist-info/RECORD
