Metadata-Version: 2.4
Name: doomarena-promptceptor
Version: 0.0.4.1
Summary: Promptceptor tool
Author-email: Gabriel Huang <gabriel.huang@servicenow.com>
Maintainer-email: Gabriel Huang <gabriel.huang@servicenow.com>
License: Apache-2.0
Project-URL: Homepage, https://github.com/ServiceNow/DoomArena/
Project-URL: Issues, https://github.com/ServiceNow/DoomArena/issues
Requires-Python: >=3.10
Requires-Dist: openai>=1.78.0
Requires-Dist: pytest
Requires-Dist: PyYAML
Requires-Dist: litellm>=1.66.3
